scrapyx_luminati/__init__.py
scrapyx_luminati/luminati.py
scrapyx_luminati-0.1.6.dist-info/METADATA
scrapyx_luminati-0.1.6.dist-info/WHEEL
scrapyx_luminati-0.1.6.dist-info/top_level.txt
scrapyx_luminati-0.1.6.dist-info/RECORD
