Metadata-Version: 2.1
Name: scrapyx-luminati
Version: 0.1.6
Summary: Luminati middleware for Scrapy
Home-page: https://github.com/tubndgit/scrapyx-luminati
Author: Henry B.
Author-email: tubnd.younet@gmail.com
License: MIT
Download-URL: https://github.com/tubndgit/scrapyx-luminati/archive/master.zip
Platform: UNKNOWN
Requires-Python: >=2.7
